README.rst
setup.py
sentry_telegram/__init__.py
sentry_telegram/plugin.py
sentry_telegram_v9.egg-info/PKG-INFO
sentry_telegram_v9.egg-info/SOURCES.txt
sentry_telegram_v9.egg-info/dependency_links.txt
sentry_telegram_v9.egg-info/top_level.txt