Metadata-Version: 1.1
Name: sentry-telegram-v9
Version: 0.3.0
Summary: Plugin for Sentry which allows sending notification via Telegram messenger.
Home-page: https://github.com/butorov/sentry-telegram
Author: Viacheslav Butorov
Author-email: butorovv@gmail.com
License: MIT
Platform: UNKNOWN
Classifier: Development Status :: 4 - Beta
Classifier: Environment :: Console
Classifier: Intended Audience :: Developers
Classifier: Intended Audience :: System Administrators
Classifier: License :: OSI Approved :: MIT License
Classifier: Operating System :: OS Independent
Classifier: Programming Language :: Python
Classifier: Programming Language :: Python :: 2.7
Classifier: Programming Language :: Python :: Implementation :: CPython
